encryptdef/__init__.py
encryptdef/__main__.py
encryptdef/cli.py
encryptdef/core.py
encryptdef/interactive_interface.py
encryptdef/log.py
encryptdef/settings.py
encryptdef/template.py
encryptdef/utils.py
encryptdef-1.0.9.dist-info/LICENSE
encryptdef-1.0.9.dist-info/METADATA
encryptdef-1.0.9.dist-info/WHEEL
encryptdef-1.0.9.dist-info/entry_points.txt
encryptdef-1.0.9.dist-info/top_level.txt
encryptdef-1.0.9.dist-info/RECORD
