Metadata-Version: 2.1
Name: encryptdef
Version: 1.0.9
Summary: Projeto em python para criptografar e descriptografar dados e arquivos de forma interativa e CLI
Author-email: Ayslan Batista <ayslan.batista@hotmail.com>
License: MIT
Project-URL: Homepage, https://github.com/AyslanBatista/encryptdef
Project-URL: Repository, https://github.com/AyslanBatista/encryptdef
Project-URL: Issues, https://github.com/AyslanBatista/encryptdef/issues
Classifier: Programming Language :: Python :: 3
Classifier: Programming Language :: Python
Classifier: Intended Audience :: Developers
Classifier: License :: OSI Approved :: MIT License
Classifier: Programming Language :: Python :: 3 :: Only
Classifier: Programming Language :: Python :: 3.10
Classifier: Programming Language :: Python :: 3.11
Classifier: Programming Language :: Python :: 3.12
Classifier: Topic :: Security :: Cryptography
Requires-Python: >=3.10
License-File: LICENSE
Requires-Dist: pycryptodomex >=3.20.0
Requires-Dist: rich-click >=1.8.2
Provides-Extra: dev
Requires-Dist: ipython ; extra == 'dev'
Requires-Dist: ipdb ; extra == 'dev'
Requires-Dist: flake8 ; extra == 'dev'
Requires-Dist: pyproject-flake8 ; extra == 'dev'
Requires-Dist: black ; extra == 'dev'
Requires-Dist: isort ; extra == 'dev'
Requires-Dist: build ; extra == 'dev'
Requires-Dist: twine ; extra == 'dev'
Requires-Dist: wheel ; extra == 'dev'
Requires-Dist: mypy ; extra == 'dev'
Requires-Dist: types-setuptools ; extra == 'dev'
Provides-Extra: test
Requires-Dist: pytest ; extra == 'test'
Requires-Dist: pytest-mock ; extra == 'test'
Requires-Dist: coverage ; extra == 'test'
Requires-Dist: pytest-cov ; extra == 'test'
